{
   "ngo": [
       {
           "Name": "Clark",
           "jobLocation": "Delhi",
           "jobCause": "Education",
           "jobDescribtion": "Reporter",
           "lastDate": 20
       },
       {
           "Name": "Clark",
           "jobLocation": "Delhi",
           "jobCause": "Education",
           "jobDescribtion": "Reporter",
           "lastDate": 20
       },
       {
           "Name": "Clark",
           "jobLocation": "Delhi",
           "jobCause": "Education",
           "jobDescribtion": "Reporter",
           "lastDate": 20
       },
       {
           "Name": "Clark",
           "jobLocation": "Delhi",
           "jobCause": "Education",
           "jobDescribtion": "Reporter",
           "lastDate": 20
       }
   ]
}
